test_figures_package/__init__.py
test_figures_package/main.py
test_figures_package-0.0.1.dist-info/METADATA
test_figures_package-0.0.1.dist-info/WHEEL
test_figures_package-0.0.1.dist-info/licenses/LICENSE
test_figures_package-0.0.1.dist-info/RECORD
