Metadata-Version: 2.1
Name: test_figures_package
Version: 0.0.1
Summary: la-la-la
Project-URL: Homepage, https://github.com/Leila132/Mindbox-test-tasks
Author-email: Leyla <saryymova@gmail.com>
License-File: LICENSE
Classifier: License :: OSI Approved :: MIT License
Classifier: Operating System :: OS Independent
Classifier: Programming Language :: Python :: 3
Requires-Python: >=3.7.0
